{
  "project_info": {
    "project_number": "479173921547",
    "project_id": "cravixy-e5ac3",
    "storage_bucket": "cravixy-e5ac3.firebasestorage.app"
  },
  "client": [
    {
      "client_info": {
        "mobilesdk_app_id": "1:479173921547:android:d9f1ea0ddff4d07e4ff00e",
        "android_client_info": {
          "package_name": "com.cravixy"
        }
      },
      "oauth_client": [
        {
          "client_id": "479173921547-ou23glhod77njnhmu00ti5vogfc8hc3o.apps.googleusercontent.com",
          "client_type": 1,
          "android_info": {
            "package_name": "com.cravixy",
            "certificate_hash": "5e8f16062ea3cd2c4a0d547876baa6f38cabf625"
          }
        },
        {
          "client_id": "479173921547-6ar08994r6bjrfjan4mo6ro8a9epv355.apps.googleusercontent.com",
          "client_type": 3
        }
      ],
      "api_key": [
        {
          "current_key": "AIzaSyCkCRRmyXnau6jGKbTvmZUSglm3xJ9leZM"
        }
      ],
      "services": {
        "appinvite_service": {
          "other_platform_oauth_client": [
            {
              "client_id": "479173921547-6ar08994r6bjrfjan4mo6ro8a9epv355.apps.googleusercontent.com",
              "client_type": 3
            }
          ]
        }
      }
    }
  ],
  "configuration_version": "1"
}